{
  "DATA_LEVEL": "School Level",
  "PUBLIC_OR_INDEPENDENT": "Public School",
  "PUBLIC": true,
  "DISTRICT_NUMBER": "008",
  "DISTRICT_NAME": "Kootenay Lake",
  "SCHOOL_NUMBER": "00807013",
  "SCHOOL_NAME": "L V Rogers Secondary",
  "SUB_POPULATION": "All Students",
  "assessments": {
    "Numeracy Assessment 10": {
      "2017/2018": {
        "ASSESSMENT_LANGUAGE": "English",
        "NUMBER_WRITERS": "215",
        "SCORE": "4138",
        "AVERAGE": "19.25"
      },
      "2018/2019": {
        "ASSESSMENT_LANGUAGE": "English",
        "NUMBER_WRITERS": "202",
        "SCORE": "3064",
        "AVERAGE": "15.17"
      },
      "2019/2020": {
        "ASSESSMENT_LANGUAGE": "English",
        "NUMBER_WRITERS": "141",
        "SCORE": "2237",
        "AVERAGE": "15.87"
      },
      "2020/2021": {
        "ASSESSMENT_LANGUAGE": "English",
        "NUMBER_WRITERS": "242",
        "SCORE": "3088",
        "AVERAGE": "12.76"
      },
      "2021/2022": {
        "ASSESSMENT_LANGUAGE": "English",
        "NUMBER_WRITERS": "190",
        "SCORE": "2940",
        "AVERAGE": "15.47"
      },
      "2022/2023": {
        "ASSESSMENT_LANGUAGE": "English",
        "NUMBER_WRITERS": "200",
        "SCORE": "2822.1",
        "AVERAGE": "14.11"
      },
      "2023/2024": {
        "ASSESSMENT_LANGUAGE": "English",
        "NUMBER_WRITERS": "203",
        "SCORE": "3174.9",
        "AVERAGE": "15.64"
      },
      "2024/2025": {
        "ASSESSMENT_LANGUAGE": "English",
        "NUMBER_WRITERS": "200",
        "SCORE": "3328.3",
        "AVERAGE": "16.64"
      }
    },
    "Literacy Assessment 10": {
      "2019/2020": {
        "ASSESSMENT_LANGUAGE": "English",
        "NUMBER_WRITERS": "106",
        "SCORE": "3742",
        "AVERAGE": "35.30"
      },
      "2020/2021": {
        "ASSESSMENT_LANGUAGE": "English",
        "NUMBER_WRITERS": "203",
        "SCORE": "7477",
        "AVERAGE": "36.83"
      },
      "2021/2022": {
        "ASSESSMENT_LANGUAGE": "English",
        "NUMBER_WRITERS": "208",
        "SCORE": "7323.8",
        "AVERAGE": "35.21"
      },
      "2022/2023": {
        "ASSESSMENT_LANGUAGE": "English",
        "NUMBER_WRITERS": "191",
        "SCORE": "6784",
        "AVERAGE": "35.52"
      },
      "2023/2024": {
        "ASSESSMENT_LANGUAGE": "English",
        "NUMBER_WRITERS": "188",
        "SCORE": "6883.5",
        "AVERAGE": "36.61"
      },
      "2024/2025": {
        "ASSESSMENT_LANGUAGE": "English",
        "NUMBER_WRITERS": "198",
        "SCORE": "6597",
        "AVERAGE": "33.32"
      }
    },
    "Literacy Assessment 12": {
      "2021/2022": {
        "ASSESSMENT_LANGUAGE": "English",
        "NUMBER_WRITERS": "175",
        "SCORE": "5787.2",
        "AVERAGE": "33.07"
      },
      "2022/2023": {
        "ASSESSMENT_LANGUAGE": "English",
        "NUMBER_WRITERS": "177",
        "SCORE": "6032.8",
        "AVERAGE": "34.08"
      },
      "2023/2024": {
        "ASSESSMENT_LANGUAGE": "English",
        "NUMBER_WRITERS": "199",
        "SCORE": "6360.6",
        "AVERAGE": "31.96"
      },
      "2024/2025": {
        "ASSESSMENT_LANGUAGE": "English",
        "NUMBER_WRITERS": "188",
        "SCORE": "5967.2",
        "AVERAGE": "31.74"
      }
    }
  }
}