{
  "DATA_LEVEL": "School Level",
  "PUBLIC_OR_INDEPENDENT": "Public School",
  "PUBLIC": true,
  "DISTRICT_NUMBER": "035",
  "DISTRICT_NAME": "Langley",
  "SCHOOL_NUMBER": "03599173",
  "SCHOOL_NAME": "Choices Program",
  "SUB_POPULATION": "All Students",
  "assessments": {
    "Numeracy Assessment 10": {
      "2019/2020": {
        "ASSESSMENT_LANGUAGE": "English",
        "NUMBER_WRITERS": "Msk",
        "SCORE": "Msk",
        "AVERAGE": 0
      },
      "2020/2021": {
        "ASSESSMENT_LANGUAGE": "English",
        "NUMBER_WRITERS": "Msk",
        "SCORE": "Msk",
        "AVERAGE": 0
      },
      "2021/2022": {
        "ASSESSMENT_LANGUAGE": "English",
        "NUMBER_WRITERS": "Msk",
        "SCORE": "Msk",
        "AVERAGE": 0
      },
      "2022/2023": {
        "ASSESSMENT_LANGUAGE": "English",
        "NUMBER_WRITERS": "11",
        "SCORE": "140",
        "AVERAGE": "12.73"
      },
      "2023/2024": {
        "ASSESSMENT_LANGUAGE": "English",
        "NUMBER_WRITERS": "Msk",
        "SCORE": "Msk",
        "AVERAGE": 0
      },
      "2024/2025": {
        "ASSESSMENT_LANGUAGE": "English",
        "NUMBER_WRITERS": "Msk",
        "SCORE": "Msk",
        "AVERAGE": 0
      }
    },
    "Literacy Assessment 10": {
      "2020/2021": {
        "ASSESSMENT_LANGUAGE": "English",
        "NUMBER_WRITERS": "Msk",
        "SCORE": "Msk",
        "AVERAGE": 0
      },
      "2021/2022": {
        "ASSESSMENT_LANGUAGE": "English",
        "NUMBER_WRITERS": "Msk",
        "SCORE": "Msk",
        "AVERAGE": 0
      },
      "2022/2023": {
        "ASSESSMENT_LANGUAGE": "English",
        "NUMBER_WRITERS": "Msk",
        "SCORE": "Msk",
        "AVERAGE": 0
      },
      "2023/2024": {
        "ASSESSMENT_LANGUAGE": "English",
        "NUMBER_WRITERS": "Msk",
        "SCORE": "Msk",
        "AVERAGE": 0
      }
    },
    "Literacy Assessment 12": {
      "2021/2022": {
        "ASSESSMENT_LANGUAGE": "English",
        "NUMBER_WRITERS": "Msk",
        "SCORE": "Msk",
        "AVERAGE": 0
      },
      "2022/2023": {
        "ASSESSMENT_LANGUAGE": "English",
        "NUMBER_WRITERS": "Msk",
        "SCORE": "Msk",
        "AVERAGE": 0
      },
      "2023/2024": {
        "ASSESSMENT_LANGUAGE": "English",
        "NUMBER_WRITERS": "Msk",
        "SCORE": "Msk",
        "AVERAGE": 0
      },
      "2024/2025": {
        "ASSESSMENT_LANGUAGE": "English",
        "NUMBER_WRITERS": "11",
        "SCORE": "294.7",
        "AVERAGE": "26.79"
      }
    }
  }
}