{
  "DATA_LEVEL": "School Level",
  "PUBLIC_OR_INDEPENDENT": "Public School",
  "DISTRICT_NUMBER": "039",
  "DISTRICT_NAME": "Vancouver",
  "SCHOOL_NUMBER": "03939011",
  "SCHOOL_NAME": "Vancouver Technical Secondary",
  "SUB_POPULATION": "All Students",
  "assessments": {
    "Numeracy Assessment 10": {
      "2017/2018": {
        "ASSESSMENT_LANGUAGE": "English",
        "NUMBER_WRITERS": "479",
        "NUMBER_EMERGING": "Msk",
        "NUMBER_DEVELOPING": "208",
        "NUMBER_PROFICIENT": "177",
        "NUMBER_EXTENDING": "Msk",
        "SCORE": "10359"
      },
      "2018/2019": {
        "ASSESSMENT_LANGUAGE": "English",
        "NUMBER_WRITERS": "301",
        "NUMBER_EMERGING": "Msk",
        "NUMBER_DEVELOPING": "131",
        "NUMBER_PROFICIENT": "86",
        "NUMBER_EXTENDING": "Msk",
        "SCORE": "5849"
      },
      "2019/2020": {
        "ASSESSMENT_LANGUAGE": "English",
        "NUMBER_WRITERS": "284",
        "NUMBER_EMERGING": "30",
        "NUMBER_DEVELOPING": "92",
        "NUMBER_PROFICIENT": "135",
        "NUMBER_EXTENDING": "27",
        "SCORE": "5629"
      },
      "2020/2021": {
        "ASSESSMENT_LANGUAGE": "English",
        "NUMBER_WRITERS": "336",
        "NUMBER_EMERGING": "Msk",
        "NUMBER_DEVELOPING": "121",
        "NUMBER_PROFICIENT": "146",
        "NUMBER_EXTENDING": "Msk",
        "SCORE": "5775"
      },
      "2021/2022": {
        "ASSESSMENT_LANGUAGE": "English",
        "NUMBER_WRITERS": "274",
        "NUMBER_EMERGING": "25",
        "NUMBER_DEVELOPING": "87",
        "NUMBER_PROFICIENT": "124",
        "NUMBER_EXTENDING": "38",
        "SCORE": "5324.6"
      },
      "2022/2023": {
        "ASSESSMENT_LANGUAGE": "English",
        "NUMBER_WRITERS": "302",
        "NUMBER_EMERGING": "Msk",
        "NUMBER_DEVELOPING": "118",
        "NUMBER_PROFICIENT": "110",
        "NUMBER_EXTENDING": "Msk",
        "SCORE": "5101.7"
      },
      "2023/2024": {
        "ASSESSMENT_LANGUAGE": "English",
        "NUMBER_WRITERS": "315",
        "NUMBER_EMERGING": "29",
        "NUMBER_DEVELOPING": "114",
        "NUMBER_PROFICIENT": "111",
        "NUMBER_EXTENDING": "61",
        "SCORE": "5896.8"
      },
      "2024/2025": {
        "ASSESSMENT_LANGUAGE": "English",
        "NUMBER_WRITERS": "315",
        "NUMBER_EMERGING": "15",
        "NUMBER_DEVELOPING": "93",
        "NUMBER_PROFICIENT": "145",
        "NUMBER_EXTENDING": "62",
        "SCORE": "6366.3"
      }
    },
    "Literacy Assessment 10": {
      "2019/2020": {
        "ASSESSMENT_LANGUAGE": "English",
        "NUMBER_WRITERS": "269",
        "NUMBER_EMERGING": "Msk",
        "NUMBER_DEVELOPING": "Msk",
        "NUMBER_PROFICIENT": "180",
        "NUMBER_EXTENDING": "60",
        "SCORE": "10880"
      },
      "2020/2021": {
        "ASSESSMENT_LANGUAGE": "English",
        "NUMBER_WRITERS": "300",
        "NUMBER_EMERGING": "13",
        "NUMBER_DEVELOPING": "51",
        "NUMBER_PROFICIENT": "202",
        "NUMBER_EXTENDING": "34",
        "SCORE": "11122"
      },
      "2021/2022": {
        "ASSESSMENT_LANGUAGE": "English",
        "NUMBER_WRITERS": "269",
        "NUMBER_EMERGING": "Msk",
        "NUMBER_DEVELOPING": "Msk",
        "NUMBER_PROFICIENT": "178",
        "NUMBER_EXTENDING": "54",
        "SCORE": "10711.6"
      },
      "2022/2023": {
        "ASSESSMENT_LANGUAGE": "English",
        "NUMBER_WRITERS": "322",
        "NUMBER_EMERGING": "Msk",
        "NUMBER_DEVELOPING": "Msk",
        "NUMBER_PROFICIENT": "197",
        "NUMBER_EXTENDING": "62",
        "SCORE": "12014.6"
      },
      "2023/2024": {
        "ASSESSMENT_LANGUAGE": "English",
        "NUMBER_WRITERS": "301",
        "NUMBER_EMERGING": "13",
        "NUMBER_DEVELOPING": "54",
        "NUMBER_PROFICIENT": "191",
        "NUMBER_EXTENDING": "43",
        "SCORE": "10860.5"
      },
      "2024/2025": {
        "ASSESSMENT_LANGUAGE": "English",
        "NUMBER_WRITERS": "297",
        "NUMBER_EMERGING": "11",
        "NUMBER_DEVELOPING": "60",
        "NUMBER_PROFICIENT": "192",
        "NUMBER_EXTENDING": "34",
        "SCORE": "10437.5"
      }
    },
    "Literacy Assessment 12": {
      "2021/2022": {
        "ASSESSMENT_LANGUAGE": "English",
        "NUMBER_WRITERS": "294",
        "NUMBER_EMERGING": "Msk",
        "NUMBER_DEVELOPING": "Msk",
        "NUMBER_PROFICIENT": "181",
        "NUMBER_EXTENDING": "80",
        "SCORE": "11279.7"
      },
      "2022/2023": {
        "ASSESSMENT_LANGUAGE": "English",
        "NUMBER_WRITERS": "290",
        "NUMBER_EMERGING": "Msk",
        "NUMBER_DEVELOPING": "Msk",
        "NUMBER_PROFICIENT": "176",
        "NUMBER_EXTENDING": "73",
        "SCORE": "10499.6"
      },
      "2023/2024": {
        "ASSESSMENT_LANGUAGE": "English",
        "NUMBER_WRITERS": "273",
        "NUMBER_EMERGING": "Msk",
        "NUMBER_DEVELOPING": "Msk",
        "NUMBER_PROFICIENT": "192",
        "NUMBER_EXTENDING": "53",
        "SCORE": "9710.4"
      },
      "2024/2025": {
        "ASSESSMENT_LANGUAGE": "English",
        "NUMBER_WRITERS": "316",
        "NUMBER_EMERGING": "Msk",
        "NUMBER_DEVELOPING": "42",
        "NUMBER_PROFICIENT": "202",
        "NUMBER_EXTENDING": "Msk",
        "SCORE": "10689.3"
      }
    }
  }
}