{
  "DATA_LEVEL": "School Level",
  "PUBLIC_OR_INDEPENDENT": "Independent School",
  "DISTRICT_NUMBER": "",
  "DISTRICT_NAME": "St Thomas More Collegiate Ltd",
  "SCHOOL_NUMBER": "04196031",
  "SCHOOL_NAME": "St Thomas More Collegiate",
  "SUB_POPULATION": "All Students",
  "assessments": {
    "Numeracy Assessment 10": {
      "2017/2018": {
        "ASSESSMENT_LANGUAGE": "English",
        "NUMBER_WRITERS": "123",
        "NUMBER_EMERGING": "Msk",
        "NUMBER_DEVELOPING": "60",
        "NUMBER_PROFICIENT": "48",
        "NUMBER_EXTENDING": "Msk",
        "SCORE": "2855"
      },
      "2018/2019": {
        "ASSESSMENT_LANGUAGE": "English",
        "NUMBER_WRITERS": "269",
        "NUMBER_EMERGING": "22",
        "NUMBER_DEVELOPING": "123",
        "NUMBER_PROFICIENT": "113",
        "NUMBER_EXTENDING": "11",
        "SCORE": "5485"
      },
      "2019/2020": {
        "ASSESSMENT_LANGUAGE": "English",
        "NUMBER_WRITERS": "147",
        "NUMBER_EMERGING": "Msk",
        "NUMBER_DEVELOPING": "43",
        "NUMBER_PROFICIENT": "86",
        "NUMBER_EXTENDING": "Msk",
        "SCORE": "3256"
      },
      "2020/2021": {
        "ASSESSMENT_LANGUAGE": "English",
        "NUMBER_WRITERS": "117",
        "NUMBER_EMERGING": "Msk",
        "NUMBER_DEVELOPING": "40",
        "NUMBER_PROFICIENT": "66",
        "NUMBER_EXTENDING": "Msk",
        "SCORE": "1928"
      },
      "2021/2022": {
        "ASSESSMENT_LANGUAGE": "English",
        "NUMBER_WRITERS": "131",
        "NUMBER_EMERGING": "Msk",
        "NUMBER_DEVELOPING": "38",
        "NUMBER_PROFICIENT": "74",
        "NUMBER_EXTENDING": "Msk",
        "SCORE": "2663.2"
      },
      "2022/2023": {
        "ASSESSMENT_LANGUAGE": "English",
        "NUMBER_WRITERS": "135",
        "NUMBER_EMERGING": "Msk",
        "NUMBER_DEVELOPING": "40",
        "NUMBER_PROFICIENT": "63",
        "NUMBER_EXTENDING": "Msk",
        "SCORE": "2775.5"
      },
      "2023/2024": {
        "ASSESSMENT_LANGUAGE": "English",
        "NUMBER_WRITERS": "130",
        "NUMBER_EMERGING": "Msk",
        "NUMBER_DEVELOPING": "29",
        "NUMBER_PROFICIENT": "69",
        "NUMBER_EXTENDING": "Msk",
        "SCORE": "2651.5"
      },
      "2024/2025": {
        "ASSESSMENT_LANGUAGE": "English",
        "NUMBER_WRITERS": "154",
        "NUMBER_EMERGING": "Msk",
        "NUMBER_DEVELOPING": "42",
        "NUMBER_PROFICIENT": "85",
        "NUMBER_EXTENDING": "Msk",
        "SCORE": "2908.3"
      }
    },
    "Literacy Assessment 10": {
      "2020/2021": {
        "ASSESSMENT_LANGUAGE": "English",
        "NUMBER_WRITERS": "258",
        "NUMBER_EMERGING": "Msk",
        "NUMBER_DEVELOPING": "Msk",
        "NUMBER_PROFICIENT": "111",
        "NUMBER_EXTENDING": "139",
        "SCORE": "11780"
      },
      "2021/2022": {
        "ASSESSMENT_LANGUAGE": "English",
        "NUMBER_WRITERS": "147",
        "NUMBER_EMERGING": "Msk",
        "NUMBER_DEVELOPING": "Msk",
        "NUMBER_PROFICIENT": "81",
        "NUMBER_EXTENDING": "60",
        "SCORE": "6634.6"
      },
      "2022/2023": {
        "ASSESSMENT_LANGUAGE": "English",
        "NUMBER_WRITERS": "134",
        "NUMBER_EMERGING": "Msk",
        "NUMBER_DEVELOPING": "Msk",
        "NUMBER_PROFICIENT": "97",
        "NUMBER_EXTENDING": "35",
        "SCORE": "5588.3"
      },
      "2023/2024": {
        "ASSESSMENT_LANGUAGE": "English",
        "NUMBER_WRITERS": "139",
        "NUMBER_EMERGING": "Msk",
        "NUMBER_DEVELOPING": "Msk",
        "NUMBER_PROFICIENT": "91",
        "NUMBER_EXTENDING": "44",
        "SCORE": "5897.5"
      },
      "2024/2025": {
        "ASSESSMENT_LANGUAGE": "English",
        "NUMBER_WRITERS": "144",
        "NUMBER_EMERGING": "Msk",
        "NUMBER_DEVELOPING": "Msk",
        "NUMBER_PROFICIENT": "101",
        "NUMBER_EXTENDING": "36",
        "SCORE": "5827"
      }
    },
    "Literacy Assessment 12": {
      "2021/2022": {
        "ASSESSMENT_LANGUAGE": "English",
        "NUMBER_WRITERS": "136",
        "NUMBER_EMERGING": "Msk",
        "NUMBER_DEVELOPING": "Msk",
        "NUMBER_PROFICIENT": "75",
        "NUMBER_EXTENDING": "53",
        "SCORE": "5599.3"
      },
      "2022/2023": {
        "ASSESSMENT_LANGUAGE": "English",
        "NUMBER_WRITERS": "126",
        "NUMBER_EMERGING": "Msk",
        "NUMBER_DEVELOPING": "Msk",
        "NUMBER_PROFICIENT": "67",
        "NUMBER_EXTENDING": "58",
        "SCORE": "5127.7"
      },
      "2023/2024": {
        "ASSESSMENT_LANGUAGE": "English",
        "NUMBER_WRITERS": "Msk",
        "NUMBER_EMERGING": "Msk",
        "NUMBER_DEVELOPING": "Msk",
        "NUMBER_PROFICIENT": "Msk",
        "NUMBER_EXTENDING": "Msk",
        "SCORE": "Msk"
      },
      "2024/2025": {
        "ASSESSMENT_LANGUAGE": "English",
        "NUMBER_WRITERS": "135",
        "NUMBER_EMERGING": "Msk",
        "NUMBER_DEVELOPING": "Msk",
        "NUMBER_PROFICIENT": "87",
        "NUMBER_EXTENDING": "46",
        "SCORE": "5096.5"
      }
    }
  }
}