{
  "DATA_LEVEL": "School Level",
  "PUBLIC_OR_INDEPENDENT": "Public School",
  "PUBLIC": true,
  "DISTRICT_NUMBER": "042",
  "DISTRICT_NAME": "Maple Ridge-Pitt Meadows",
  "SCHOOL_NUMBER": "04299153",
  "SCHOOL_NAME": "Outreach Alternate Secondary",
  "SUB_POPULATION": "All Students",
  "assessments": {
    "Numeracy Assessment 10": {
      "2017/2018": {
        "ASSESSMENT_LANGUAGE": "English",
        "NUMBER_WRITERS": null,
        "SCORE": null,
        "AVERAGE": null
      },
      "2018/2019": {
        "ASSESSMENT_LANGUAGE": "English",
        "NUMBER_WRITERS": "34",
        "SCORE": "200",
        "AVERAGE": 15.08
      },
      "2019/2020": {
        "ASSESSMENT_LANGUAGE": "English",
        "NUMBER_WRITERS": "42",
        "SCORE": "292",
        "AVERAGE": 17.83
      },
      "2020/2021": {
        "ASSESSMENT_LANGUAGE": "English",
        "NUMBER_WRITERS": "15",
        "SCORE": "120",
        "AVERAGE": 20.51
      },
      "2021/2022": {
        "ASSESSMENT_LANGUAGE": "English",
        "NUMBER_WRITERS": "19",
        "SCORE": "201.9",
        "AVERAGE": 27.25
      },
      "2022/2023": {
        "ASSESSMENT_LANGUAGE": "English",
        "NUMBER_WRITERS": null,
        "SCORE": null,
        "AVERAGE": null
      },
      "2023/2024": {
        "ASSESSMENT_LANGUAGE": "English",
        "NUMBER_WRITERS": "12",
        "SCORE": "117.6",
        "AVERAGE": 25.13
      },
      "2024/2025": {
        "ASSESSMENT_LANGUAGE": "English",
        "NUMBER_WRITERS": "12",
        "SCORE": "138.9",
        "AVERAGE": 29.68
      }
    },
    "Literacy Assessment 10": {
      "2019/2020": {
        "ASSESSMENT_LANGUAGE": "English",
        "NUMBER_WRITERS": null,
        "SCORE": null,
        "AVERAGE": null
      },
      "2020/2021": {
        "ASSESSMENT_LANGUAGE": "English",
        "NUMBER_WRITERS": null,
        "SCORE": null,
        "AVERAGE": null
      },
      "2021/2022": {
        "ASSESSMENT_LANGUAGE": "English",
        "NUMBER_WRITERS": null,
        "SCORE": null,
        "AVERAGE": null
      },
      "2022/2023": {
        "ASSESSMENT_LANGUAGE": "English",
        "NUMBER_WRITERS": "13",
        "SCORE": "369.4",
        "AVERAGE": 47.36
      },
      "2023/2024": {
        "ASSESSMENT_LANGUAGE": "English",
        "NUMBER_WRITERS": null,
        "SCORE": null,
        "AVERAGE": null
      },
      "2024/2025": {
        "ASSESSMENT_LANGUAGE": "English",
        "NUMBER_WRITERS": "14",
        "SCORE": "364.5",
        "AVERAGE": 43.39
      }
    },
    "Literacy Assessment 12": {
      "2021/2022": {
        "ASSESSMENT_LANGUAGE": "English",
        "NUMBER_WRITERS": "30",
        "SCORE": "757.7",
        "AVERAGE": 45.92
      },
      "2022/2023": {
        "ASSESSMENT_LANGUAGE": "English",
        "NUMBER_WRITERS": "40",
        "SCORE": "919.5",
        "AVERAGE": 41.8
      },
      "2023/2024": {
        "ASSESSMENT_LANGUAGE": "English",
        "NUMBER_WRITERS": "37",
        "SCORE": "855.7",
        "AVERAGE": 42.05
      },
      "2024/2025": {
        "ASSESSMENT_LANGUAGE": "English",
        "NUMBER_WRITERS": "52",
        "SCORE": "1090.9",
        "AVERAGE": 38.14
      }
    }
  }
}