{
  "DATA_LEVEL": "School Level",
  "PUBLIC_OR_INDEPENDENT": "Public School",
  "PUBLIC": true,
  "DISTRICT_NUMBER": "054",
  "DISTRICT_NAME": "Bulkley Valley",
  "SCHOOL_NUMBER": "05454013",
  "SCHOOL_NAME": "Smithers Secondary",
  "SUB_POPULATION": "All Students",
  "assessments": {
    "Numeracy Assessment 10": {
      "2017/2018": {
        "ASSESSMENT_LANGUAGE": "English",
        "NUMBER_WRITERS": "176",
        "SCORE": "3390",
        "AVERAGE": 49.39
      },
      "2018/2019": {
        "ASSESSMENT_LANGUAGE": "English",
        "NUMBER_WRITERS": "129",
        "SCORE": "1645",
        "AVERAGE": 32.7
      },
      "2019/2020": {
        "ASSESSMENT_LANGUAGE": "English",
        "NUMBER_WRITERS": "43",
        "SCORE": "575",
        "AVERAGE": 34.29
      },
      "2020/2021": {
        "ASSESSMENT_LANGUAGE": "English",
        "NUMBER_WRITERS": "168",
        "SCORE": "1809",
        "AVERAGE": 27.61
      },
      "2021/2022": {
        "ASSESSMENT_LANGUAGE": "English",
        "NUMBER_WRITERS": "106",
        "SCORE": "1366.5",
        "AVERAGE": 33.06
      },
      "2022/2023": {
        "ASSESSMENT_LANGUAGE": "English",
        "NUMBER_WRITERS": "115",
        "SCORE": "1422.6",
        "AVERAGE": 31.72
      },
      "2023/2024": {
        "ASSESSMENT_LANGUAGE": "English",
        "NUMBER_WRITERS": "113",
        "SCORE": "1529.7",
        "AVERAGE": 34.71
      },
      "2024/2025": {
        "ASSESSMENT_LANGUAGE": "English",
        "NUMBER_WRITERS": "129",
        "SCORE": "1807.6",
        "AVERAGE": 35.93
      }
    },
    "Literacy Assessment 10": {
      "2019/2020": {
        "ASSESSMENT_LANGUAGE": "English",
        "NUMBER_WRITERS": "47",
        "SCORE": "1607",
        "AVERAGE": 56.99
      },
      "2020/2021": {
        "ASSESSMENT_LANGUAGE": "English",
        "NUMBER_WRITERS": "134",
        "SCORE": "4358",
        "AVERAGE": 54.2
      },
      "2021/2022": {
        "ASSESSMENT_LANGUAGE": "English",
        "NUMBER_WRITERS": "113",
        "SCORE": "3697.3",
        "AVERAGE": 54.53
      },
      "2022/2023": {
        "ASSESSMENT_LANGUAGE": "English",
        "NUMBER_WRITERS": "113",
        "SCORE": "3238.3",
        "AVERAGE": 47.76
      },
      "2023/2024": {
        "ASSESSMENT_LANGUAGE": "English",
        "NUMBER_WRITERS": "109",
        "SCORE": "3123",
        "AVERAGE": 47.75
      },
      "2024/2025": {
        "ASSESSMENT_LANGUAGE": "English",
        "NUMBER_WRITERS": "136",
        "SCORE": "4453.5",
        "AVERAGE": 54.58
      }
    },
    "Literacy Assessment 12": {
      "2021/2022": {
        "ASSESSMENT_LANGUAGE": "English",
        "NUMBER_WRITERS": "90",
        "SCORE": "2701.4",
        "AVERAGE": 54.57
      },
      "2022/2023": {
        "ASSESSMENT_LANGUAGE": "English",
        "NUMBER_WRITERS": "99",
        "SCORE": "2938.9",
        "AVERAGE": 53.97
      },
      "2023/2024": {
        "ASSESSMENT_LANGUAGE": "English",
        "NUMBER_WRITERS": "94",
        "SCORE": "2527.9",
        "AVERAGE": 48.9
      },
      "2024/2025": {
        "ASSESSMENT_LANGUAGE": "English",
        "NUMBER_WRITERS": "107",
        "SCORE": "2497.6",
        "AVERAGE": 42.44
      }
    }
  }
}