{
  "DATA_LEVEL": "School Level",
  "PUBLIC_OR_INDEPENDENT": "Independent School",
  "DISTRICT_NUMBER": "",
  "DISTRICT_NAME": "Cedars Christian School",
  "SCHOOL_NUMBER": "05796230",
  "SCHOOL_NAME": "Cedars Christian School",
  "SUB_POPULATION": "All Students",
  "assessments": {
    "Numeracy Assessment 10": {
      "2017/2018": {
        "ASSESSMENT_LANGUAGE": "English",
        "NUMBER_WRITERS": "10",
        "NUMBER_EMERGING": "Msk",
        "NUMBER_DEVELOPING": "Msk",
        "NUMBER_PROFICIENT": "Msk",
        "NUMBER_EXTENDING": "Msk",
        "SCORE": "242"
      },
      "2018/2019": {
        "ASSESSMENT_LANGUAGE": "English",
        "NUMBER_WRITERS": "41",
        "NUMBER_EMERGING": "16",
        "NUMBER_DEVELOPING": "22",
        "NUMBER_PROFICIENT": "Msk",
        "NUMBER_EXTENDING": "Msk",
        "SCORE": "525"
      },
      "2019/2020": {
        "ASSESSMENT_LANGUAGE": "English",
        "NUMBER_WRITERS": "25",
        "NUMBER_EMERGING": "Msk",
        "NUMBER_DEVELOPING": "12",
        "NUMBER_PROFICIENT": "Msk",
        "NUMBER_EXTENDING": "Msk",
        "SCORE": "342"
      },
      "2020/2021": {
        "ASSESSMENT_LANGUAGE": "English",
        "NUMBER_WRITERS": "29",
        "NUMBER_EMERGING": "Msk",
        "NUMBER_DEVELOPING": "10",
        "NUMBER_PROFICIENT": "13",
        "NUMBER_EXTENDING": "Msk",
        "SCORE": "404"
      },
      "2021/2022": {
        "ASSESSMENT_LANGUAGE": "English",
        "NUMBER_WRITERS": "29",
        "NUMBER_EMERGING": "Msk",
        "NUMBER_DEVELOPING": "Msk",
        "NUMBER_PROFICIENT": "12",
        "NUMBER_EXTENDING": "Msk",
        "SCORE": "597.1"
      },
      "2022/2023": {
        "ASSESSMENT_LANGUAGE": "English",
        "NUMBER_WRITERS": "34",
        "NUMBER_EMERGING": "Msk",
        "NUMBER_DEVELOPING": "Msk",
        "NUMBER_PROFICIENT": "20",
        "NUMBER_EXTENDING": "Msk",
        "SCORE": "635.9"
      },
      "2023/2024": {
        "ASSESSMENT_LANGUAGE": "English",
        "NUMBER_WRITERS": "31",
        "NUMBER_EMERGING": "Msk",
        "NUMBER_DEVELOPING": "11",
        "NUMBER_PROFICIENT": "11",
        "NUMBER_EXTENDING": "Msk",
        "SCORE": "676.1"
      },
      "2024/2025": {
        "ASSESSMENT_LANGUAGE": "English",
        "NUMBER_WRITERS": "31",
        "NUMBER_EMERGING": "Msk",
        "NUMBER_DEVELOPING": "15",
        "NUMBER_PROFICIENT": "12",
        "NUMBER_EXTENDING": "Msk",
        "SCORE": "497"
      }
    },
    "Literacy Assessment 10": {
      "2020/2021": {
        "ASSESSMENT_LANGUAGE": "English",
        "NUMBER_WRITERS": "44",
        "NUMBER_EMERGING": "",
        "NUMBER_DEVELOPING": "Msk",
        "NUMBER_PROFICIENT": "34",
        "NUMBER_EXTENDING": "Msk",
        "SCORE": "1769"
      },
      "2021/2022": {
        "ASSESSMENT_LANGUAGE": "English",
        "NUMBER_WRITERS": "26",
        "NUMBER_EMERGING": "Msk",
        "NUMBER_DEVELOPING": "Msk",
        "NUMBER_PROFICIENT": "20",
        "NUMBER_EXTENDING": "Msk",
        "SCORE": "1005.5"
      },
      "2022/2023": {
        "ASSESSMENT_LANGUAGE": "English",
        "NUMBER_WRITERS": "34",
        "NUMBER_EMERGING": "",
        "NUMBER_DEVELOPING": "Msk",
        "NUMBER_PROFICIENT": "22",
        "NUMBER_EXTENDING": "Msk",
        "SCORE": "1236.6"
      },
      "2023/2024": {
        "ASSESSMENT_LANGUAGE": "English",
        "NUMBER_WRITERS": "28",
        "NUMBER_EMERGING": "Msk",
        "NUMBER_DEVELOPING": "Msk",
        "NUMBER_PROFICIENT": "18",
        "NUMBER_EXTENDING": "Msk",
        "SCORE": "1058"
      },
      "2024/2025": {
        "ASSESSMENT_LANGUAGE": "English",
        "NUMBER_WRITERS": "32",
        "NUMBER_EMERGING": "",
        "NUMBER_DEVELOPING": "Msk",
        "NUMBER_PROFICIENT": "25",
        "NUMBER_EXTENDING": "Msk",
        "SCORE": "1113"
      }
    },
    "Literacy Assessment 12": {
      "2021/2022": {
        "ASSESSMENT_LANGUAGE": "English",
        "NUMBER_WRITERS": "23",
        "NUMBER_EMERGING": "Msk",
        "NUMBER_DEVELOPING": "Msk",
        "NUMBER_PROFICIENT": "14",
        "NUMBER_EXTENDING": "Msk",
        "SCORE": "865.8"
      },
      "2022/2023": {
        "ASSESSMENT_LANGUAGE": "English",
        "NUMBER_WRITERS": "21",
        "NUMBER_EMERGING": "Msk",
        "NUMBER_DEVELOPING": "Msk",
        "NUMBER_PROFICIENT": "15",
        "NUMBER_EXTENDING": "Msk",
        "SCORE": "769.8"
      },
      "2023/2024": {
        "ASSESSMENT_LANGUAGE": "English",
        "NUMBER_WRITERS": "27",
        "NUMBER_EMERGING": "Msk",
        "NUMBER_DEVELOPING": "Msk",
        "NUMBER_PROFICIENT": "15",
        "NUMBER_EXTENDING": "Msk",
        "SCORE": "934.8"
      },
      "2024/2025": {
        "ASSESSMENT_LANGUAGE": "English",
        "NUMBER_WRITERS": "30",
        "NUMBER_EMERGING": "",
        "NUMBER_DEVELOPING": "Msk",
        "NUMBER_PROFICIENT": "19",
        "NUMBER_EXTENDING": "Msk",
        "SCORE": "989.5"
      }
    }
  }
}