{
  "DATA_LEVEL": "School Level",
  "PUBLIC_OR_INDEPENDENT": "Public School",
  "PUBLIC": true,
  "DISTRICT_NUMBER": "061",
  "DISTRICT_NAME": "Greater Victoria",
  "SCHOOL_NUMBER": "06161018",
  "SCHOOL_NAME": "Victoria High",
  "SUB_POPULATION": "All Students",
  "assessments": {
    "Numeracy Assessment 10": {
      "2017/2018": {
        "ASSESSMENT_LANGUAGE": "English",
        "NUMBER_WRITERS": "91",
        "SCORE": "1668",
        "AVERAGE": "18.33"
      },
      "2018/2019": {
        "ASSESSMENT_LANGUAGE": "English",
        "NUMBER_WRITERS": "162",
        "SCORE": "2508",
        "AVERAGE": "15.48"
      },
      "2019/2020": {
        "ASSESSMENT_LANGUAGE": "English",
        "NUMBER_WRITERS": "299",
        "SCORE": "3996",
        "AVERAGE": "13.36"
      },
      "2020/2021": {
        "ASSESSMENT_LANGUAGE": "English",
        "NUMBER_WRITERS": "192",
        "SCORE": "2322",
        "AVERAGE": "12.09"
      },
      "2021/2022": {
        "ASSESSMENT_LANGUAGE": "English",
        "NUMBER_WRITERS": "165",
        "SCORE": "2291.7",
        "AVERAGE": "13.89"
      },
      "2022/2023": {
        "ASSESSMENT_LANGUAGE": "English",
        "NUMBER_WRITERS": "179",
        "SCORE": "2049.9",
        "AVERAGE": "11.45"
      },
      "2023/2024": {
        "ASSESSMENT_LANGUAGE": "English",
        "NUMBER_WRITERS": "266",
        "SCORE": "3728.6",
        "AVERAGE": "14.02"
      },
      "2024/2025": {
        "ASSESSMENT_LANGUAGE": "English",
        "NUMBER_WRITERS": "152",
        "SCORE": "2223.8",
        "AVERAGE": "14.63"
      }
    },
    "Literacy Assessment 10": {
      "2019/2020": {
        "ASSESSMENT_LANGUAGE": "English",
        "NUMBER_WRITERS": "76",
        "SCORE": "2385",
        "AVERAGE": "31.38"
      },
      "2020/2021": {
        "ASSESSMENT_LANGUAGE": "English",
        "NUMBER_WRITERS": "227",
        "SCORE": "7788",
        "AVERAGE": "34.31"
      },
      "2021/2022": {
        "ASSESSMENT_LANGUAGE": "English",
        "NUMBER_WRITERS": "161",
        "SCORE": "5490.5",
        "AVERAGE": "34.10"
      },
      "2022/2023": {
        "ASSESSMENT_LANGUAGE": "English",
        "NUMBER_WRITERS": "191",
        "SCORE": "6327.3",
        "AVERAGE": "33.13"
      },
      "2023/2024": {
        "ASSESSMENT_LANGUAGE": "English",
        "NUMBER_WRITERS": "258",
        "SCORE": "8475.5",
        "AVERAGE": "32.85"
      },
      "2024/2025": {
        "ASSESSMENT_LANGUAGE": "English",
        "NUMBER_WRITERS": "247",
        "SCORE": "7828.5",
        "AVERAGE": "31.69"
      }
    },
    "Literacy Assessment 12": {
      "2021/2022": {
        "ASSESSMENT_LANGUAGE": "English",
        "NUMBER_WRITERS": "146",
        "SCORE": "4866.7",
        "AVERAGE": "33.33"
      },
      "2022/2023": {
        "ASSESSMENT_LANGUAGE": "English",
        "NUMBER_WRITERS": "171",
        "SCORE": "5008.5",
        "AVERAGE": "29.29"
      },
      "2023/2024": {
        "ASSESSMENT_LANGUAGE": "English",
        "NUMBER_WRITERS": "145",
        "SCORE": "4342.8",
        "AVERAGE": "29.95"
      },
      "2024/2025": {
        "ASSESSMENT_LANGUAGE": "English",
        "NUMBER_WRITERS": "178",
        "SCORE": "5073",
        "AVERAGE": "28.50"
      }
    }
  }
}