{
  "DATA_LEVEL": "School Level",
  "PUBLIC_OR_INDEPENDENT": "Public School",
  "PUBLIC": true,
  "DISTRICT_NUMBER": "061",
  "DISTRICT_NAME": "Greater Victoria",
  "SCHOOL_NUMBER": "06161057",
  "SCHOOL_NAME": "Reynolds Secondary",
  "SUB_POPULATION": "All Students",
  "assessments": {
    "Numeracy Assessment 10": {
      "2017/2018": {
        "ASSESSMENT_LANGUAGE": "English",
        "NUMBER_WRITERS": null,
        "SCORE": null,
        "AVERAGE": null
      },
      "2018/2019": {
        "ASSESSMENT_LANGUAGE": "English",
        "NUMBER_WRITERS": "380",
        "SCORE": "6703",
        "AVERAGE": 45.23
      },
      "2019/2020": {
        "ASSESSMENT_LANGUAGE": "English",
        "NUMBER_WRITERS": "232",
        "SCORE": "3789",
        "AVERAGE": 41.88
      },
      "2020/2021": {
        "ASSESSMENT_LANGUAGE": "English",
        "NUMBER_WRITERS": "209",
        "SCORE": "3559",
        "AVERAGE": 43.66
      },
      "2021/2022": {
        "ASSESSMENT_LANGUAGE": "English",
        "NUMBER_WRITERS": "217",
        "SCORE": "4066.5",
        "AVERAGE": 48.05
      },
      "2022/2023": {
        "ASSESSMENT_LANGUAGE": "English",
        "NUMBER_WRITERS": "220",
        "SCORE": "3419.8",
        "AVERAGE": 39.86
      },
      "2023/2024": {
        "ASSESSMENT_LANGUAGE": "English",
        "NUMBER_WRITERS": "218",
        "SCORE": "3891.5",
        "AVERAGE": 45.77
      },
      "2024/2025": {
        "ASSESSMENT_LANGUAGE": "English",
        "NUMBER_WRITERS": "242",
        "SCORE": "4097.7",
        "AVERAGE": 43.42
      }
    },
    "Literacy Assessment 10": {
      "2019/2020": {
        "ASSESSMENT_LANGUAGE": "English",
        "NUMBER_WRITERS": "217",
        "SCORE": "7546",
        "AVERAGE": 57.96
      },
      "2020/2021": {
        "ASSESSMENT_LANGUAGE": "English",
        "NUMBER_WRITERS": "211",
        "SCORE": "7930",
        "AVERAGE": 62.64
      },
      "2021/2022": {
        "ASSESSMENT_LANGUAGE": "English",
        "NUMBER_WRITERS": "227",
        "SCORE": "8013.8",
        "AVERAGE": 58.84
      },
      "2022/2023": {
        "ASSESSMENT_LANGUAGE": "English",
        "NUMBER_WRITERS": "213",
        "SCORE": "7889",
        "AVERAGE": 61.73
      },
      "2023/2024": {
        "ASSESSMENT_LANGUAGE": "English",
        "NUMBER_WRITERS": "256",
        "SCORE": "8736",
        "AVERAGE": 56.88
      },
      "2024/2025": {
        "ASSESSMENT_LANGUAGE": "English",
        "NUMBER_WRITERS": "214",
        "SCORE": "7421.5",
        "AVERAGE": 57.8
      }
    },
    "Literacy Assessment 12": {
      "2021/2022": {
        "ASSESSMENT_LANGUAGE": "English",
        "NUMBER_WRITERS": "223",
        "SCORE": "7692.9",
        "AVERAGE": 62.72
      },
      "2022/2023": {
        "ASSESSMENT_LANGUAGE": "English",
        "NUMBER_WRITERS": "214",
        "SCORE": "7098.9",
        "AVERAGE": 60.31
      },
      "2023/2024": {
        "ASSESSMENT_LANGUAGE": "English",
        "NUMBER_WRITERS": "202",
        "SCORE": "5990.1",
        "AVERAGE": 53.92
      },
      "2024/2025": {
        "ASSESSMENT_LANGUAGE": "English",
        "NUMBER_WRITERS": "213",
        "SCORE": "6576.8",
        "AVERAGE": 56.14
      }
    }
  }
}