{
  "DATA_LEVEL": "School Level",
  "PUBLIC_OR_INDEPENDENT": "Public School",
  "PUBLIC": true,
  "DISTRICT_NUMBER": "091",
  "DISTRICT_NAME": "Nechako Lakes",
  "SCHOOL_NUMBER": "09191023",
  "SCHOOL_NAME": "Lakes District Secondary",
  "SUB_POPULATION": "All Students",
  "assessments": {
    "Numeracy Assessment 10": {
      "2017/2018": {
        "ASSESSMENT_LANGUAGE": "English",
        "NUMBER_WRITERS": "80",
        "SCORE": "1137",
        "AVERAGE": "14.21"
      },
      "2018/2019": {
        "ASSESSMENT_LANGUAGE": "English",
        "NUMBER_WRITERS": "62",
        "SCORE": "747",
        "AVERAGE": "12.05"
      },
      "2019/2020": {
        "ASSESSMENT_LANGUAGE": "English",
        "NUMBER_WRITERS": "37",
        "SCORE": "222",
        "AVERAGE": "6.00"
      },
      "2020/2021": {
        "ASSESSMENT_LANGUAGE": "English",
        "NUMBER_WRITERS": "84",
        "SCORE": "733",
        "AVERAGE": "8.73"
      },
      "2021/2022": {
        "ASSESSMENT_LANGUAGE": "English",
        "NUMBER_WRITERS": "55",
        "SCORE": "622",
        "AVERAGE": "11.31"
      },
      "2022/2023": {
        "ASSESSMENT_LANGUAGE": "English",
        "NUMBER_WRITERS": "60",
        "SCORE": "678.3",
        "AVERAGE": "11.30"
      },
      "2023/2024": {
        "ASSESSMENT_LANGUAGE": "English",
        "NUMBER_WRITERS": "77",
        "SCORE": "942.3",
        "AVERAGE": "12.24"
      },
      "2024/2025": {
        "ASSESSMENT_LANGUAGE": "English",
        "NUMBER_WRITERS": "59",
        "SCORE": "648",
        "AVERAGE": "10.98"
      }
    },
    "Literacy Assessment 10": {
      "2019/2020": {
        "ASSESSMENT_LANGUAGE": "English",
        "NUMBER_WRITERS": "14",
        "SCORE": "437",
        "AVERAGE": "31.21"
      },
      "2020/2021": {
        "ASSESSMENT_LANGUAGE": "English",
        "NUMBER_WRITERS": "75",
        "SCORE": "1874",
        "AVERAGE": "24.99"
      },
      "2021/2022": {
        "ASSESSMENT_LANGUAGE": "English",
        "NUMBER_WRITERS": "78",
        "SCORE": "2319.8",
        "AVERAGE": "29.74"
      },
      "2022/2023": {
        "ASSESSMENT_LANGUAGE": "English",
        "NUMBER_WRITERS": "58",
        "SCORE": "1690.8",
        "AVERAGE": "29.15"
      },
      "2023/2024": {
        "ASSESSMENT_LANGUAGE": "English",
        "NUMBER_WRITERS": "66",
        "SCORE": "2029.5",
        "AVERAGE": "30.75"
      },
      "2024/2025": {
        "ASSESSMENT_LANGUAGE": "English",
        "NUMBER_WRITERS": "68",
        "SCORE": "1843",
        "AVERAGE": "27.10"
      }
    },
    "Literacy Assessment 12": {
      "2021/2022": {
        "ASSESSMENT_LANGUAGE": "English",
        "NUMBER_WRITERS": "55",
        "SCORE": "1612",
        "AVERAGE": "29.31"
      },
      "2022/2023": {
        "ASSESSMENT_LANGUAGE": "English",
        "NUMBER_WRITERS": "46",
        "SCORE": "1325.8",
        "AVERAGE": "28.82"
      },
      "2023/2024": {
        "ASSESSMENT_LANGUAGE": "English",
        "NUMBER_WRITERS": "52",
        "SCORE": "1484.2",
        "AVERAGE": "28.54"
      },
      "2024/2025": {
        "ASSESSMENT_LANGUAGE": "English",
        "NUMBER_WRITERS": "47",
        "SCORE": "1150.4",
        "AVERAGE": "24.48"
      }
    }
  }
}